{
	"pvpPatch":
	{
		"patchRewardProb":
		[
			{
				"-3":0.2,
				"-2":0.3,
				"-1":0.5,
				"0":0.6,
				"1":0.7,
				"2":0.8,
				"3":1
			},
			{
				"-3":0.1,
				"-2":0.15,
				"-1":0.25,
				"0":0.3,
				"1":0.35,
				"2":0.4,
				"3":0.5
			},
			{
				"-3":0.06667,
				"-2":0.1,
				"-1":0.16667,
				"0":0.2,
				"1":0.23334,
				"2":0.26667,
				"3":0.33334
			}
		],
		"fakeDataProb":
		{
			"fakeDataWeight":5000,
			"maxWeightBase":10000,
			"maxWeightAdd":1000
		},
		"fakeData":
		{
			"1":
			{
				"playerLevel":1,
				"npcLevel":2,
				"fakeDataFormation":
				{
					"1":
					{
						"playerName":"Dr. Wave",
						"formation":[101001,101002]
					},
					"2":
					{
						"playerName":"Captain No.9",
						"formation":[101003,101004]
					}
				}
			},
			"2":
			{
				"playerLevel":2,
				"npcLevel":4,
				"fakeDataFormation":
				{
					"1":
					{
						"playerName":"Krillin King",
						"formation":[101005,101006,101007]
					},
					"2":
					{
						"playerName":"General Gohan",
						"formation":[101008,101009,101010]
					}
				}
			},
			"3":
			{
				"playerLevel":3,
				"npcLevel":6,
				"fakeDataFormation":
				{
					"1":
					{
						"playerName":"Legion Krillin ",
						"formation":[101001,101002,101003]
					},
					"2":
					{
						"playerName":"Amy No.17",
						"formation":[101005,101004,101009]
					}
				}
			},
			"4":
			{
				"playerLevel":4,
				"npcLevel":8,
				"fakeDataFormation":
				{
					"1":
					{
						"playerName":"Hermit Wolf",
						"formation":[101011,101012,101013,101014]
					},
					"2":
					{
						"playerName":"Shen JR..",
						"formation":[101001,101002,101003,101004]
					}
				}
			},
			"5":
			{
				"playerLevel":5,
				"npcLevel":10,
				"fakeDataFormation":
				{
					"1":
					{
						"playerName":"Prince Rage",
						"formation":[101001,101002,101011,101013]
					},
					"2":
					{
						"playerName":"Shen King",
						"formation":[101003,101004,101005,101006]
					}
				}
			},
			"6":
			{
				"playerLevel":6,
				"npcLevel":12,
				"fakeDataFormation":
				{
					"1":
					{
						"playerName":"North Kai No.15",
						"formation":[101021,101022,101023,101024]
					},
					"2":
					{
						"playerName":"Jeice No.14",
						"formation":[101031,101032,101033,101034]
					}
				}
			},
			"7":
			{
				"playerLevel":7,
				"npcLevel":14,
				"fakeDataFormation":
				{
					"1":
					{
						"playerName":"Korin No.12",
						"formation":[101001,101011,101021,101031]
					},
					"2":
					{
						"playerName":"Baby Legion",
						"formation":[101001,101005,101010,101015]
					}
				}
			},
			"8":
			{
				"playerLevel":8,
				"npcLevel":16,
				"fakeDataFormation":
				{
					"1":
					{
						"playerName":"Dr. Wave",
						"formation":[101001,101002,101006,101008]
					},
					"2":
					{
						"playerName":"Captain No.9",
						"formation":[101003,101004,101012,101021]
					}
				}
			},
			"9":
			{
				"playerLevel":9,
				"npcLevel":18,
				"fakeDataFormation":
				{
					"1":
					{
						"playerName":"Krillin King",
						"formation":[101005,101006,101007,101031]
					},
					"2":
					{
						"playerName":"General Gohan",
						"formation":[101008,101009,101010,101031]
					}
				}
			},
			"10":
			{
				"playerLevel":10,
				"npcLevel":20,
				"fakeDataFormation":
				{
					"1":
					{
						"playerName":"Legion Krillin ",
						"formation":[101001,101002,101003,101011]
					},
					"2":
					{
						"playerName":"Amy No.17",
						"formation":[101005,101004,101009,101013]
					}
				}
			},
			"11":
			{
				"playerLevel":11,
				"npcLevel":22,
				"fakeDataFormation":
				{
					"1":
					{
						"playerName":"Hermit Wolf",
						"formation":[101011,101012,101013,101014,101015]
					},
					"2":
					{
						"playerName":"Shen JR..",
						"formation":[101001,101002,101003,101004,101005]
					}
				}
			},
			"12":
			{
				"playerLevel":12,
				"npcLevel":24,
				"fakeDataFormation":
				{
					"1":
					{
						"playerName":"Prince Rage",
						"formation":[101001,101002,101011,101013,101021]
					},
					"2":
					{
						"playerName":"Shen King",
						"formation":[101003,101004,101005,101006,101007]
					}
				}
			},
			"13":
			{
				"playerLevel":13,
				"npcLevel":26,
				"fakeDataFormation":
				{
					"1":
					{
						"playerName":"North Kai No.15",
						"formation":[101021,101022,101023,101024,101025]
					},
					"2":
					{
						"playerName":"Jeice No.14",
						"formation":[101031,101032,101033,101034,101035]
					}
				}
			},
			"14":
			{
				"playerLevel":14,
				"npcLevel":28,
				"fakeDataFormation":
				{
					"1":
					{
						"playerName":"Korin No.12",
						"formation":[101001,101011,101021,101031,101041]
					},
					"2":
					{
						"playerName":"Baby Legion",
						"formation":[101001,101005,101010,101015,101020]
					}
				}
			},
			"15":
			{
				"playerLevel":15,
				"npcLevel":30,
				"fakeDataFormation":
				{
					"1":
					{
						"playerName":"Dr. Wave",
						"formation":[101001,101002,101006,101008,101009]
					},
					"2":
					{
						"playerName":"Captain No.9",
						"formation":[101003,101004,101012,101021,101019]
					}
				}
			},
			"16":
			{
				"playerLevel":16,
				"npcLevel":32,
				"fakeDataFormation":
				{
					"1":
					{
						"playerName":"Krillin King",
						"formation":[101005,101006,101007,101031,101022,101009]
					},
					"2":
					{
						"playerName":"General Gohan",
						"formation":[101008,101009,101010,101031,101011,101012]
					}
				}
			},
			"17":
			{
				"playerLevel":17,
				"npcLevel":34,
				"fakeDataFormation":
				{
					"1":
					{
						"playerName":"Legion Krillin ",
						"formation":[101001,101002,101003,101011,101015,101007]
					},
					"2":
					{
						"playerName":"Amy No.17",
						"formation":[101005,101004,101009,101013,101019,101022]
					}
				}
			},
			"18":
			{
				"playerLevel":18,
				"npcLevel":36,
				"fakeDataFormation":
				{
					"1":
					{
						"playerName":"Hermit Wolf",
						"formation":[101011,101012,101013,101014,101015,101016]
					},
					"2":
					{
						"playerName":"Shen JR..",
						"formation":[101001,101002,101003,101004,101005,101006]
					}
				}
			},
			"19":
			{
				"playerLevel":19,
				"npcLevel":38,
				"fakeDataFormation":
				{
					"1":
					{
						"playerName":"Prince Rage",
						"formation":[101001,101002,101011,101013,101021,101015]
					},
					"2":
					{
						"playerName":"Shen King",
						"formation":[101003,101004,101005,101006,101007,101008]
					}
				}
			},
			"20":
			{
				"playerLevel":20,
				"npcLevel":40,
				"fakeDataFormation":
				{
					"1":
					{
						"playerName":"North Kai No.15",
						"formation":[101021,101022,101023,101024,101025,101026]
					},
					"2":
					{
						"playerName":"Jeice No.14",
						"formation":[101031,101032,101033,101034,101035,101036]
					}
				}
			},
			"21":
			{
				"playerLevel":21,
				"npcLevel":42,
				"fakeDataFormation":
				{
					"1":
					{
						"playerName":"Korin No.12",
						"formation":[101001,101011,101021,101031,101041,101002,101012]
					},
					"2":
					{
						"playerName":"Baby Legion",
						"formation":[101001,101005,101010,101015,101020,101025,101030]
					}
				}
			},
			"22":
			{
				"playerLevel":22,
				"npcLevel":44,
				"fakeDataFormation":
				{
					"1":
					{
						"playerName":"Dr. Wave",
						"formation":[101001,101002,101006,101008,101009,101011,101013]
					},
					"2":
					{
						"playerName":"Captain No.9",
						"formation":[101003,101004,101012,101021,101019,101041,101042]
					}
				}
			},
			"23":
			{
				"playerLevel":23,
				"npcLevel":46,
				"fakeDataFormation":
				{
					"1":
					{
						"playerName":"Krillin King",
						"formation":[101005,101006,101007,101031,101022,101009,101011]
					},
					"2":
					{
						"playerName":"General Gohan",
						"formation":[101008,101009,101010,101031,101011,101012,101025]
					}
				}
			},
			"24":
			{
				"playerLevel":24,
				"npcLevel":48,
				"fakeDataFormation":
				{
					"1":
					{
						"playerName":"Legion Krillin ",
						"formation":[101001,101002,101003,101011,101015,101007,101017]
					},
					"2":
					{
						"playerName":"Amy No.17",
						"formation":[101005,101004,101009,101013,101019,101022,101025]
					}
				}
			},
			"25":
			{
				"playerLevel":25,
				"npcLevel":50,
				"fakeDataFormation":
				{
					"1":
					{
						"playerName":"Hermit Wolf",
						"formation":[101011,101012,101013,101014,101015,101016,101017]
					},
					"2":
					{
						"playerName":"Shen JR..",
						"formation":[101001,101002,101003,101004,101005,101006,101007]
					}
				}
			},
			"26":
			{
				"playerLevel":26,
				"npcLevel":52,
				"fakeDataFormation":
				{
					"1":
					{
						"playerName":"Prince Rage",
						"formation":[101001,101002,101011,101013,101021,101015,101022,101041]
					},
					"2":
					{
						"playerName":"Shen King",
						"formation":[101003,101004,101005,101006,101007,101008,101009,101010]
					}
				}
			},
			"27":
			{
				"playerLevel":27,
				"npcLevel":54,
				"fakeDataFormation":
				{
					"1":
					{
						"playerName":"North Kai No.15",
						"formation":[101021,101022,101023,101024,101025,101026,101027,101028]
					},
					"2":
					{
						"playerName":"Jeice No.14",
						"formation":[101031,101032,101033,101034,101035,101036,101037,101038]
					}
				}
			},
			"28":
			{
				"playerLevel":28,
				"npcLevel":56,
				"fakeDataFormation":
				{
					"1":
					{
						"playerName":"Korin No.12",
						"formation":[101001,101011,101021,101031,101041,101002,101012,101022]
					},
					"2":
					{
						"playerName":"Baby Legion",
						"formation":[101001,101005,101010,101015,101020,101025,101030,101035]
					}
				}
			},
			"29":
			{
				"playerLevel":29,
				"npcLevel":58,
				"fakeDataFormation":
				{
					"1":
					{
						"playerName":"Dr. Wave",
						"formation":[101001,101002,101006,101008,101009,101011,101013,101015]
					},
					"2":
					{
						"playerName":"Captain No.9",
						"formation":[101003,101004,101012,101021,101019,101041,101042,101018]
					}
				}
			},
			"30":
			{
				"playerLevel":30,
				"npcLevel":60,
				"fakeDataFormation":
				{
					"1":
					{
						"playerName":"Krillin King",
						"formation":[101005,101006,101007,101031,101022,101009,101011,101029]
					},
					"2":
					{
						"playerName":"General Gohan",
						"formation":[101008,101009,101010,101031,101011,101012,101025,101033]
					}
				}
			},
			"31":
			{
				"playerLevel":31,
				"npcLevel":62,
				"fakeDataFormation":
				{
					"1":
					{
						"playerName":"Legion Krillin ",
						"formation":[101001,101002,101003,101011,101015,101007,101017,101027]
					},
					"2":
					{
						"playerName":"Amy No.17",
						"formation":[101005,101004,101009,101013,101019,101022,101025,101038]
					}
				}
			},
			"32":
			{
				"playerLevel":32,
				"npcLevel":64,
				"fakeDataFormation":
				{
					"1":
					{
						"playerName":"Hermit Wolf",
						"formation":[101011,101012,101013,101014,101015,101016,101017,101018]
					},
					"2":
					{
						"playerName":"Shen JR..",
						"formation":[101001,101002,101003,101004,101005,101006,101007,101008]
					}
				}
			},
			"33":
			{
				"playerLevel":33,
				"npcLevel":66,
				"fakeDataFormation":
				{
					"1":
					{
						"playerName":"Prince Rage",
						"formation":[101001,101002,101011,101013,101021,101015,101022,101041]
					},
					"2":
					{
						"playerName":"Shen King",
						"formation":[101003,101004,101005,101006,101007,101008,101009,101010]
					}
				}
			},
			"34":
			{
				"playerLevel":34,
				"npcLevel":68,
				"fakeDataFormation":
				{
					"1":
					{
						"playerName":"North Kai No.15",
						"formation":[101021,101022,101023,101024,101025,101026,101027,101028]
					},
					"2":
					{
						"playerName":"Jeice No.14",
						"formation":[101031,101032,101033,101034,101035,101036,101037,101038]
					}
				}
			},
			"35":
			{
				"playerLevel":35,
				"npcLevel":70,
				"fakeDataFormation":
				{
					"1":
					{
						"playerName":"Korin No.12",
						"formation":[101001,101011,101021,101031,101041,101002,101012,101022]
					},
					"2":
					{
						"playerName":"Baby Legion",
						"formation":[101001,101005,101010,101015,101020,101025,101030,101035]
					}
				}
			},
			"36":
			{
				"playerLevel":36,
				"npcLevel":72,
				"fakeDataFormation":
				{
					"1":
					{
						"playerName":"Dr. Wave",
						"formation":[101001,101002,101006,101008,101009,101011,101013,101015]
					},
					"2":
					{
						"playerName":"Captain No.9",
						"formation":[101003,101004,101012,101021,101019,101041,101042,101018]
					}
				}
			},
			"37":
			{
				"playerLevel":37,
				"npcLevel":74,
				"fakeDataFormation":
				{
					"1":
					{
						"playerName":"Krillin King",
						"formation":[101005,101006,101007,101031,101022,101009,101011,101029]
					},
					"2":
					{
						"playerName":"General Gohan",
						"formation":[101008,101009,101010,101031,101011,101012,101025,101033]
					}
				}
			},
			"38":
			{
				"playerLevel":38,
				"npcLevel":76,
				"fakeDataFormation":
				{
					"1":
					{
						"playerName":"Legion Krillin ",
						"formation":[101001,101002,101003,101011,101015,101007,101017,101027]
					},
					"2":
					{
						"playerName":"Amy No.17",
						"formation":[101005,101004,101009,101013,101019,101022,101025,101038]
					}
				}
			},
			"39":
			{
				"playerLevel":39,
				"npcLevel":78,
				"fakeDataFormation":
				{
					"1":
					{
						"playerName":"Hermit Wolf",
						"formation":[101011,101012,101013,101014,101015,101016,101017,101018]
					},
					"2":
					{
						"playerName":"Shen JR..",
						"formation":[101001,101002,101003,101004,101005,101006,101007,101008]
					}
				}
			},
			"40":
			{
				"playerLevel":40,
				"npcLevel":80,
				"fakeDataFormation":
				{
					"1":
					{
						"playerName":"Prince Rage",
						"formation":[101001,101002,101011,101013,101021,101015,101022,101041]
					},
					"2":
					{
						"playerName":"Shen King",
						"formation":[101003,101004,101005,101006,101007,101008,101009,101010]
					}
				}
			},
			"41":
			{
				"playerLevel":41,
				"npcLevel":82,
				"fakeDataFormation":
				{
					"1":
					{
						"playerName":"North Kai No.15",
						"formation":[101021,101022,101023,101024,101025,101026,101027,101028]
					},
					"2":
					{
						"playerName":"Jeice No.14",
						"formation":[101031,101032,101033,101034,101035,101036,101037,101038]
					}
				}
			},
			"42":
			{
				"playerLevel":42,
				"npcLevel":84,
				"fakeDataFormation":
				{
					"1":
					{
						"playerName":"Korin No.12",
						"formation":[101001,101011,101021,101031,101041,101002,101012,101022]
					},
					"2":
					{
						"playerName":"Baby Legion",
						"formation":[101001,101005,101010,101015,101020,101025,101030,101035]
					}
				}
			},
			"43":
			{
				"playerLevel":43,
				"npcLevel":86,
				"fakeDataFormation":
				{
					"1":
					{
						"playerName":"Dr. Wave",
						"formation":[101001,101002,101006,101008,101009,101011,101013,101015]
					},
					"2":
					{
						"playerName":"Captain No.9",
						"formation":[101003,101004,101012,101021,101019,101041,101042,101018]
					}
				}
			},
			"44":
			{
				"playerLevel":44,
				"npcLevel":88,
				"fakeDataFormation":
				{
					"1":
					{
						"playerName":"Krillin King",
						"formation":[101005,101006,101007,101031,101022,101009,101011,101029]
					},
					"2":
					{
						"playerName":"General Gohan",
						"formation":[101008,101009,101010,101031,101011,101012,101025,101033]
					}
				}
			},
			"45":
			{
				"playerLevel":45,
				"npcLevel":90,
				"fakeDataFormation":
				{
					"1":
					{
						"playerName":"Legion Krillin ",
						"formation":[101001,101002,101003,101011,101015,101007,101017,101027]
					},
					"2":
					{
						"playerName":"Amy No.17",
						"formation":[101005,101004,101009,101013,101019,101022,101025,101038]
					}
				}
			},
			"46":
			{
				"playerLevel":46,
				"npcLevel":92,
				"fakeDataFormation":
				{
					"1":
					{
						"playerName":"Hermit Wolf",
						"formation":[101011,101012,101013,101014,101015,101016,101017,101018]
					},
					"2":
					{
						"playerName":"Shen JR..",
						"formation":[101001,101002,101003,101004,101005,101006,101007,101008]
					}
				}
			},
			"47":
			{
				"playerLevel":47,
				"npcLevel":94,
				"fakeDataFormation":
				{
					"1":
					{
						"playerName":"Prince Rage",
						"formation":[101001,101002,101011,101013,101021,101015,101022,101041]
					},
					"2":
					{
						"playerName":"Shen King",
						"formation":[101003,101004,101005,101006,101007,101008,101009,101010]
					}
				}
			},
			"48":
			{
				"playerLevel":48,
				"npcLevel":96,
				"fakeDataFormation":
				{
					"1":
					{
						"playerName":"North Kai No.15",
						"formation":[101021,101022,101023,101024,101025,101026,101027,101028]
					},
					"2":
					{
						"playerName":"Jeice No.14",
						"formation":[101031,101032,101033,101034,101035,101036,101037,101038]
					}
				}
			},
			"49":
			{
				"playerLevel":49,
				"npcLevel":98,
				"fakeDataFormation":
				{
					"1":
					{
						"playerName":"Korin No.12",
						"formation":[101001,101011,101021,101031,101041,101002,101012,101022]
					},
					"2":
					{
						"playerName":"Baby Legion",
						"formation":[101001,101005,101010,101015,101020,101025,101030,101035]
					}
				}
			},
			"50":
			{
				"playerLevel":50,
				"npcLevel":100,
				"fakeDataFormation":
				{
					"1":
					{
						"playerName":"Dr. Wave",
						"formation":[101001,101002,101006,101008,101009,101011,101013,101015]
					},
					"2":
					{
						"playerName":"Captain No.9",
						"formation":[101003,101004,101012,101021,101019,101041,101042,101018]
					}
				}
			},
			"51":
			{
				"playerLevel":51,
				"npcLevel":102,
				"fakeDataFormation":
				{
					"1":
					{
						"playerName":"Krillin King",
						"formation":[101005,101006,101007,101031,101022,101009,101011,101029]
					},
					"2":
					{
						"playerName":"General Gohan",
						"formation":[101008,101009,101010,101031,101011,101012,101025,101033]
					}
				}
			},
			"52":
			{
				"playerLevel":52,
				"npcLevel":104,
				"fakeDataFormation":
				{
					"1":
					{
						"playerName":"Legion Krillin ",
						"formation":[101001,101002,101003,101011,101015,101007,101017,101027]
					},
					"2":
					{
						"playerName":"Amy No.17",
						"formation":[101005,101004,101009,101013,101019,101022,101025,101038]
					}
				}
			},
			"53":
			{
				"playerLevel":53,
				"npcLevel":106,
				"fakeDataFormation":
				{
					"1":
					{
						"playerName":"Hermit Wolf",
						"formation":[101011,101012,101013,101014,101015,101016,101017,101018]
					},
					"2":
					{
						"playerName":"Shen JR..",
						"formation":[101001,101002,101003,101004,101005,101006,101007,101008]
					}
				}
			},
			"54":
			{
				"playerLevel":54,
				"npcLevel":108,
				"fakeDataFormation":
				{
					"1":
					{
						"playerName":"Prince Rage",
						"formation":[101001,101002,101011,101013,101021,101015,101022,101041]
					},
					"2":
					{
						"playerName":"Shen King",
						"formation":[101003,101004,101005,101006,101007,101008,101009,101010]
					}
				}
			},
			"55":
			{
				"playerLevel":55,
				"npcLevel":110,
				"fakeDataFormation":
				{
					"1":
					{
						"playerName":"North Kai No.15",
						"formation":[101021,101022,101023,101024,101025,101026,101027,101028]
					},
					"2":
					{
						"playerName":"Jeice No.14",
						"formation":[101031,101032,101033,101034,101035,101036,101037,101038]
					}
				}
			},
			"56":
			{
				"playerLevel":56,
				"npcLevel":112,
				"fakeDataFormation":
				{
					"1":
					{
						"playerName":"Korin No.12",
						"formation":[101001,101011,101021,101031,101041,101002,101012,101022]
					},
					"2":
					{
						"playerName":"Baby Legion",
						"formation":[101001,101005,101010,101015,101020,101025,101030,101035]
					}
				}
			},
			"57":
			{
				"playerLevel":57,
				"npcLevel":114,
				"fakeDataFormation":
				{
					"1":
					{
						"playerName":"Dr. Wave",
						"formation":[101001,101002,101006,101008,101009,101011,101013,101015]
					},
					"2":
					{
						"playerName":"Captain No.9",
						"formation":[101003,101004,101012,101021,101019,101041,101042,101018]
					}
				}
			},
			"58":
			{
				"playerLevel":58,
				"npcLevel":116,
				"fakeDataFormation":
				{
					"1":
					{
						"playerName":"Krillin King",
						"formation":[101005,101006,101007,101031,101022,101009,101011,101029]
					},
					"2":
					{
						"playerName":"General Gohan",
						"formation":[101008,101009,101010,101031,101011,101012,101025,101033]
					}
				}
			},
			"59":
			{
				"playerLevel":59,
				"npcLevel":118,
				"fakeDataFormation":
				{
					"1":
					{
						"playerName":"Legion Krillin ",
						"formation":[101001,101002,101003,101011,101015,101007,101017,101027]
					},
					"2":
					{
						"playerName":"Amy No.17",
						"formation":[101005,101004,101009,101013,101019,101022,101025,101038]
					}
				}
			},
			"60":
			{
				"playerLevel":60,
				"npcLevel":120,
				"fakeDataFormation":
				{
					"1":
					{
						"playerName":"Hermit Wolf",
						"formation":[101011,101012,101013,101014,101015,101016,101017,101018]
					},
					"2":
					{
						"playerName":"Shen JR..",
						"formation":[101001,101002,101003,101004,101005,101006,101007,101008]
					}
				}
			},
			"61":
			{
				"playerLevel":61,
				"npcLevel":122,
				"fakeDataFormation":
				{
					"1":
					{
						"playerName":"Prince Rage",
						"formation":[101001,101002,101011,101013,101021,101015,101022,101041]
					},
					"2":
					{
						"playerName":"Shen King",
						"formation":[101003,101004,101005,101006,101007,101008,101009,101010]
					}
				}
			},
			"62":
			{
				"playerLevel":62,
				"npcLevel":124,
				"fakeDataFormation":
				{
					"1":
					{
						"playerName":"North Kai No.15",
						"formation":[101021,101022,101023,101024,101025,101026,101027,101028]
					},
					"2":
					{
						"playerName":"Jeice No.14",
						"formation":[101031,101032,101033,101034,101035,101036,101037,101038]
					}
				}
			},
			"63":
			{
				"playerLevel":63,
				"npcLevel":126,
				"fakeDataFormation":
				{
					"1":
					{
						"playerName":"Korin No.12",
						"formation":[101001,101011,101021,101031,101041,101002,101012,101022]
					},
					"2":
					{
						"playerName":"Baby Legion",
						"formation":[101001,101005,101010,101015,101020,101025,101030,101035]
					}
				}
			},
			"64":
			{
				"playerLevel":64,
				"npcLevel":128,
				"fakeDataFormation":
				{
					"1":
					{
						"playerName":"Dr. Wave",
						"formation":[101001,101002,101006,101008,101009,101011,101013,101015]
					},
					"2":
					{
						"playerName":"Captain No.9",
						"formation":[101003,101004,101012,101021,101019,101041,101042,101018]
					}
				}
			},
			"65":
			{
				"playerLevel":65,
				"npcLevel":130,
				"fakeDataFormation":
				{
					"1":
					{
						"playerName":"Krillin King",
						"formation":[101005,101006,101007,101031,101022,101009,101011,101029]
					},
					"2":
					{
						"playerName":"General Gohan",
						"formation":[101008,101009,101010,101031,101011,101012,101025,101033]
					}
				}
			},
			"66":
			{
				"playerLevel":66,
				"npcLevel":132,
				"fakeDataFormation":
				{
					"1":
					{
						"playerName":"Legion Krillin ",
						"formation":[101001,101002,101003,101011,101015,101007,101017,101027]
					},
					"2":
					{
						"playerName":"Amy No.17",
						"formation":[101005,101004,101009,101013,101019,101022,101025,101038]
					}
				}
			},
			"67":
			{
				"playerLevel":67,
				"npcLevel":134,
				"fakeDataFormation":
				{
					"1":
					{
						"playerName":"Hermit Wolf",
						"formation":[101011,101012,101013,101014,101015,101016,101017,101018]
					},
					"2":
					{
						"playerName":"Shen JR..",
						"formation":[101001,101002,101003,101004,101005,101006,101007,101008]
					}
				}
			},
			"68":
			{
				"playerLevel":68,
				"npcLevel":136,
				"fakeDataFormation":
				{
					"1":
					{
						"playerName":"Prince Rage",
						"formation":[101001,101002,101011,101013,101021,101015,101022,101041]
					},
					"2":
					{
						"playerName":"Shen King",
						"formation":[101003,101004,101005,101006,101007,101008,101009,101010]
					}
				}
			},
			"69":
			{
				"playerLevel":69,
				"npcLevel":138,
				"fakeDataFormation":
				{
					"1":
					{
						"playerName":"North Kai No.15",
						"formation":[101021,101022,101023,101024,101025,101026,101027,101028]
					},
					"2":
					{
						"playerName":"Jeice No.14",
						"formation":[101031,101032,101033,101034,101035,101036,101037,101038]
					}
				}
			},
			"70":
			{
				"playerLevel":70,
				"npcLevel":140,
				"fakeDataFormation":
				{
					"1":
					{
						"playerName":"Korin No.12",
						"formation":[101001,101011,101021,101031,101041,101002,101012,101022]
					},
					"2":
					{
						"playerName":"Baby Legion",
						"formation":[101001,101005,101010,101015,101020,101025,101030,101035]
					}
				}
			},
			"71":
			{
				"playerLevel":71,
				"npcLevel":142,
				"fakeDataFormation":
				{
					"1":
					{
						"playerName":"Dr. Wave",
						"formation":[101001,101002,101006,101008,101009,101011,101013,101015]
					},
					"2":
					{
						"playerName":"Captain No.9",
						"formation":[101003,101004,101012,101021,101019,101041,101042,101018]
					}
				}
			},
			"72":
			{
				"playerLevel":72,
				"npcLevel":144,
				"fakeDataFormation":
				{
					"1":
					{
						"playerName":"Krillin King",
						"formation":[101005,101006,101007,101031,101022,101009,101011,101029]
					},
					"2":
					{
						"playerName":"General Gohan",
						"formation":[101008,101009,101010,101031,101011,101012,101025,101033]
					}
				}
			},
			"73":
			{
				"playerLevel":73,
				"npcLevel":146,
				"fakeDataFormation":
				{
					"1":
					{
						"playerName":"Legion Krillin ",
						"formation":[101001,101002,101003,101011,101015,101007,101017,101027]
					},
					"2":
					{
						"playerName":"Amy No.17",
						"formation":[101005,101004,101009,101013,101019,101022,101025,101038]
					}
				}
			},
			"74":
			{
				"playerLevel":74,
				"npcLevel":148,
				"fakeDataFormation":
				{
					"1":
					{
						"playerName":"Hermit Wolf",
						"formation":[101011,101012,101013,101014,101015,101016,101017,101018]
					},
					"2":
					{
						"playerName":"Shen JR..",
						"formation":[101001,101002,101003,101004,101005,101006,101007,101008]
					}
				}
			},
			"75":
			{
				"playerLevel":75,
				"npcLevel":150,
				"fakeDataFormation":
				{
					"1":
					{
						"playerName":"Prince Rage",
						"formation":[101001,101002,101011,101013,101021,101015,101022,101041]
					},
					"2":
					{
						"playerName":"Shen King",
						"formation":[101003,101004,101005,101006,101007,101008,101009,101010]
					}
				}
			},
			"76":
			{
				"playerLevel":76,
				"npcLevel":152,
				"fakeDataFormation":
				{
					"1":
					{
						"playerName":"North Kai No.15",
						"formation":[101021,101022,101023,101024,101025,101026,101027,101028]
					},
					"2":
					{
						"playerName":"Jeice No.14",
						"formation":[101031,101032,101033,101034,101035,101036,101037,101038]
					}
				}
			},
			"77":
			{
				"playerLevel":77,
				"npcLevel":154,
				"fakeDataFormation":
				{
					"1":
					{
						"playerName":"Korin No.12",
						"formation":[101001,101011,101021,101031,101041,101002,101012,101022]
					},
					"2":
					{
						"playerName":"Baby Legion",
						"formation":[101001,101005,101010,101015,101020,101025,101030,101035]
					}
				}
			},
			"78":
			{
				"playerLevel":78,
				"npcLevel":156,
				"fakeDataFormation":
				{
					"1":
					{
						"playerName":"Dr. Wave",
						"formation":[101001,101002,101006,101008,101009,101011,101013,101015]
					},
					"2":
					{
						"playerName":"Captain No.9",
						"formation":[101003,101004,101012,101021,101019,101041,101042,101018]
					}
				}
			},
			"79":
			{
				"playerLevel":79,
				"npcLevel":158,
				"fakeDataFormation":
				{
					"1":
					{
						"playerName":"Krillin King",
						"formation":[101005,101006,101007,101031,101022,101009,101011,101029]
					},
					"2":
					{
						"playerName":"General Gohan",
						"formation":[101008,101009,101010,101031,101011,101012,101025,101033]
					}
				}
			},
			"80":
			{
				"playerLevel":80,
				"npcLevel":160,
				"fakeDataFormation":
				{
					"1":
					{
						"playerName":"Legion Krillin ",
						"formation":[101001,101002,101003,101011,101015,101007,101017,101027]
					},
					"2":
					{
						"playerName":"Amy No.17",
						"formation":[101005,101004,101009,101013,101019,101022,101025,101038]
					}
				}
			},
			"81":
			{
				"playerLevel":81,
				"npcLevel":162,
				"fakeDataFormation":
				{
					"1":
					{
						"playerName":"Hermit Wolf",
						"formation":[101011,101012,101013,101014,101015,101016,101017,101018]
					},
					"2":
					{
						"playerName":"Shen JR..",
						"formation":[101001,101002,101003,101004,101005,101006,101007,101008]
					}
				}
			},
			"82":
			{
				"playerLevel":82,
				"npcLevel":164,
				"fakeDataFormation":
				{
					"1":
					{
						"playerName":"Prince Rage",
						"formation":[101001,101002,101011,101013,101021,101015,101022,101041]
					},
					"2":
					{
						"playerName":"Shen King",
						"formation":[101003,101004,101005,101006,101007,101008,101009,101010]
					}
				}
			},
			"83":
			{
				"playerLevel":83,
				"npcLevel":166,
				"fakeDataFormation":
				{
					"1":
					{
						"playerName":"North Kai No.15",
						"formation":[101021,101022,101023,101024,101025,101026,101027,101028]
					},
					"2":
					{
						"playerName":"Jeice No.14",
						"formation":[101031,101032,101033,101034,101035,101036,101037,101038]
					}
				}
			},
			"84":
			{
				"playerLevel":84,
				"npcLevel":168,
				"fakeDataFormation":
				{
					"1":
					{
						"playerName":"Korin No.12",
						"formation":[101001,101011,101021,101031,101041,101002,101012,101022]
					},
					"2":
					{
						"playerName":"Baby Legion",
						"formation":[101001,101005,101010,101015,101020,101025,101030,101035]
					}
				}
			},
			"85":
			{
				"playerLevel":85,
				"npcLevel":170,
				"fakeDataFormation":
				{
					"1":
					{
						"playerName":"Dr. Wave",
						"formation":[101001,101002,101006,101008,101009,101011,101013,101015]
					},
					"2":
					{
						"playerName":"Captain No.9",
						"formation":[101003,101004,101012,101021,101019,101041,101042,101018]
					}
				}
			},
			"86":
			{
				"playerLevel":86,
				"npcLevel":172,
				"fakeDataFormation":
				{
					"1":
					{
						"playerName":"Krillin King",
						"formation":[101005,101006,101007,101031,101022,101009,101011,101029]
					},
					"2":
					{
						"playerName":"General Gohan",
						"formation":[101008,101009,101010,101031,101011,101012,101025,101033]
					}
				}
			},
			"87":
			{
				"playerLevel":87,
				"npcLevel":174,
				"fakeDataFormation":
				{
					"1":
					{
						"playerName":"Legion Krillin ",
						"formation":[101001,101002,101003,101011,101015,101007,101017,101027]
					},
					"2":
					{
						"playerName":"Amy No.17",
						"formation":[101005,101004,101009,101013,101019,101022,101025,101038]
					}
				}
			},
			"88":
			{
				"playerLevel":88,
				"npcLevel":176,
				"fakeDataFormation":
				{
					"1":
					{
						"playerName":"Hermit Wolf",
						"formation":[101011,101012,101013,101014,101015,101016,101017,101018]
					},
					"2":
					{
						"playerName":"Shen JR..",
						"formation":[101001,101002,101003,101004,101005,101006,101007,101008]
					}
				}
			},
			"89":
			{
				"playerLevel":89,
				"npcLevel":178,
				"fakeDataFormation":
				{
					"1":
					{
						"playerName":"Prince Rage",
						"formation":[101001,101002,101011,101013,101021,101015,101022,101041]
					},
					"2":
					{
						"playerName":"Shen King",
						"formation":[101003,101004,101005,101006,101007,101008,101009,101010]
					}
				}
			},
			"90":
			{
				"playerLevel":90,
				"npcLevel":180,
				"fakeDataFormation":
				{
					"1":
					{
						"playerName":"North Kai No.15",
						"formation":[101021,101022,101023,101024,101025,101026,101027,101028]
					},
					"2":
					{
						"playerName":"Jeice No.14",
						"formation":[101031,101032,101033,101034,101035,101036,101037,101038]
					}
				}
			},
			"91":
			{
				"playerLevel":91,
				"npcLevel":182,
				"fakeDataFormation":
				{
					"1":
					{
						"playerName":"Korin No.12",
						"formation":[101001,101011,101021,101031,101041,101002,101012,101022]
					},
					"2":
					{
						"playerName":"Baby Legion",
						"formation":[101001,101005,101010,101015,101020,101025,101030,101035]
					}
				}
			},
			"92":
			{
				"playerLevel":92,
				"npcLevel":184,
				"fakeDataFormation":
				{
					"1":
					{
						"playerName":"Dr. Wave",
						"formation":[101001,101002,101006,101008,101009,101011,101013,101015]
					},
					"2":
					{
						"playerName":"Captain No.9",
						"formation":[101003,101004,101012,101021,101019,101041,101042,101018]
					}
				}
			},
			"93":
			{
				"playerLevel":93,
				"npcLevel":186,
				"fakeDataFormation":
				{
					"1":
					{
						"playerName":"Krillin King",
						"formation":[101005,101006,101007,101031,101022,101009,101011,101029]
					},
					"2":
					{
						"playerName":"General Gohan",
						"formation":[101008,101009,101010,101031,101011,101012,101025,101033]
					}
				}
			},
			"94":
			{
				"playerLevel":94,
				"npcLevel":188,
				"fakeDataFormation":
				{
					"1":
					{
						"playerName":"Legion Krillin ",
						"formation":[101001,101002,101003,101011,101015,101007,101017,101027]
					},
					"2":
					{
						"playerName":"Amy No.17",
						"formation":[101005,101004,101009,101013,101019,101022,101025,101038]
					}
				}
			},
			"95":
			{
				"playerLevel":95,
				"npcLevel":190,
				"fakeDataFormation":
				{
					"1":
					{
						"playerName":"Hermit Wolf",
						"formation":[101011,101012,101013,101014,101015,101016,101017,101018]
					},
					"2":
					{
						"playerName":"Shen JR..",
						"formation":[101001,101002,101003,101004,101005,101006,101007,101008]
					}
				}
			},
			"96":
			{
				"playerLevel":96,
				"npcLevel":192,
				"fakeDataFormation":
				{
					"1":
					{
						"playerName":"Prince Rage",
						"formation":[101001,101002,101011,101013,101021,101015,101022,101041]
					},
					"2":
					{
						"playerName":"Shen King",
						"formation":[101003,101004,101005,101006,101007,101008,101009,101010]
					}
				}
			},
			"97":
			{
				"playerLevel":97,
				"npcLevel":194,
				"fakeDataFormation":
				{
					"1":
					{
						"playerName":"North Kai No.15",
						"formation":[101021,101022,101023,101024,101025,101026,101027,101028]
					},
					"2":
					{
						"playerName":"Jeice No.14",
						"formation":[101031,101032,101033,101034,101035,101036,101037,101038]
					}
				}
			},
			"98":
			{
				"playerLevel":98,
				"npcLevel":196,
				"fakeDataFormation":
				{
					"1":
					{
						"playerName":"Korin No.12",
						"formation":[101001,101011,101021,101031,101041,101002,101012,101022]
					},
					"2":
					{
						"playerName":"Baby Legion",
						"formation":[101001,101005,101010,101015,101020,101025,101030,101035]
					}
				}
			},
			"99":
			{
				"playerLevel":99,
				"npcLevel":198,
				"fakeDataFormation":
				{
					"1":
					{
						"playerName":"Dr. Wave",
						"formation":[101001,101002,101006,101008,101009,101011,101013,101015]
					},
					"2":
					{
						"playerName":"Captain No.9",
						"formation":[101003,101004,101012,101021,101019,101041,101042,101018]
					}
				}
			},
			"100":
			{
				"playerLevel":100,
				"npcLevel":200,
				"fakeDataFormation":
				{
					"1":
					{
						"playerName":"Krillin King",
						"formation":[101005,101006,101007,101031,101022,101009,101011,101029]
					},
					"2":
					{
						"playerName":"General Gohan",
						"formation":[101008,101009,101010,101031,101011,101012,101025,101033]
					}
				}
			},
			"101":
			{
				"playerLevel":101,
				"npcLevel":202,
				"fakeDataFormation":
				{
					"1":
					{
						"playerName":"Legion Krillin ",
						"formation":[101001,101002,101003,101011,101015,101007,101017,101027]
					},
					"2":
					{
						"playerName":"Amy No.17",
						"formation":[101005,101004,101009,101013,101019,101022,101025,101038]
					}
				}
			},
			"102":
			{
				"playerLevel":102,
				"npcLevel":204,
				"fakeDataFormation":
				{
					"1":
					{
						"playerName":"Hermit Wolf",
						"formation":[101011,101012,101013,101014,101015,101016,101017,101018]
					},
					"2":
					{
						"playerName":"Shen JR..",
						"formation":[101001,101002,101003,101004,101005,101006,101007,101008]
					}
				}
			},
			"103":
			{
				"playerLevel":103,
				"npcLevel":206,
				"fakeDataFormation":
				{
					"1":
					{
						"playerName":"Prince Rage",
						"formation":[101001,101002,101011,101013,101021,101015,101022,101041]
					},
					"2":
					{
						"playerName":"Shen King",
						"formation":[101003,101004,101005,101006,101007,101008,101009,101010]
					}
				}
			},
			"104": {			
				"playerLevel": 104,		
				"npcLevel": 208,		
				"fakeDataFormation": {		
					"1": {	
						"playerName": "North Kai No.15",
						"formation": [101021,101022,101023,101024,101025,101026,101027,101028]
					},	
					"2": {	
						"playerName": "Jeice No.14",
						"formation": [101031,101032,101033,101034,101035,101036,101037,101038]
					}	
				}		
			},			
			"105": {			
				"playerLevel": 105,		
				"npcLevel": 210,		
				"fakeDataFormation": {		
					"1": {	
						"playerName": "Korin No.12",
						"formation": [101001,101011,101021,101031,101041,101002,101012,101022]
					},	
					"2": {	
						"playerName": "Baby Legion",
						"formation": [101001,101005,101010,101015,101020,101025,101030,101035]
					}	
				}		
			},			
			"106": {			
				"playerLevel": 106,		
				"npcLevel": 212,		
				"fakeDataFormation": {		
					"1": {	
						"playerName": "Dr. Wave",
						"formation": [101001,101002,101006,101008,101009,101011,101013,101015]
					},	
					"2": {	
						"playerName": "Captain No.9",
						"formation": [101003,101004,101012,101021,101019,101041,101042,101018]
					}	
				}		
			},			
			"107": {			
				"playerLevel": 107,		
				"npcLevel": 214,		
				"fakeDataFormation": {		
					"1": {	
						"playerName": "Krillin King",
						"formation": [101005,101006,101007,101031,101022,101009,101011,101029]
					},	
					"2": {	
						"playerName": "General Gohan",
						"formation": [101008,101009,101010,101031,101011,101012,101025,101033]
					}	
				}		
			},			
			"108": {			
				"playerLevel": 108,		
				"npcLevel": 216,		
				"fakeDataFormation": {		
					"1": {	
						"playerName": "Legion Krillin",
						"formation": [101001,101002,101003,101011,101015,101007,101017,101027]
					},	
					"2": {	
						"playerName": "Amy No.17",
						"formation": [101005,101004,101009,101013,101019,101022,101025,101038]
					}	
				}		
			},			
			"109": {			
				"playerLevel": 109,		
				"npcLevel": 218,		
				"fakeDataFormation": {		
					"1": {	
						"playerName": "Hermit Wolf",
						"formation": [101011,101012,101013,101014,101015,101016,101017,101018]
					},	
					"2": {	
						"playerName": "Shen JR.",
						"formation": [101001,101002,101003,101004,101005,101006,101007,101008]
					}	
				}		
			},			
			"110": {			
				"playerLevel": 110,		
				"npcLevel": 220,		
				"fakeDataFormation": {		
					"1": {	
						"playerName": "Prince Rage",
						"formation": [101001,101002,101011,101013,101021,101015,101022,101041]
					},	
					"2": {	
						"playerName": "Shen King",
						"formation": [101003,101004,101005,101006,101007,101008,101009,101010]
					}	
				}		
			},			
			"111": {			
				"playerLevel": 111,		
				"npcLevel": 222,		
				"fakeDataFormation": {		
					"1": {	
						"playerName": "North Kai No.15",
						"formation": [101021,101022,101023,101024,101025,101026,101027,101028]
					},	
					"2": {	
						"playerName": "Jeice No.14",
						"formation": [101031,101032,101033,101034,101035,101036,101037,101038]
					}	
				}		
			},			
			"112": {			
				"playerLevel": 112,		
				"npcLevel": 224,		
				"fakeDataFormation": {		
					"1": {	
						"playerName": "Korin No.12",
						"formation": [101001,101011,101021,101031,101041,101002,101012,101022]
					},	
					"2": {	
						"playerName": "Baby Legion",
						"formation": [101001,101005,101010,101015,101020,101025,101030,101035]
					}	
				}		
			},			
			"113": {			
				"playerLevel": 113,		
				"npcLevel": 226,		
				"fakeDataFormation": {		
					"1": {	
						"playerName": "Dr. Wave",
						"formation": [101001,101002,101006,101008,101009,101011,101013,101015]
					},	
					"2": {	
						"playerName": "Captain No.9",
						"formation": [101003,101004,101012,101021,101019,101041,101042,101018]
					}	
				}		
			},			
			"114": {			
				"playerLevel": 114,		
				"npcLevel": 228,		
				"fakeDataFormation": {		
					"1": {	
						"playerName": "Krillin King",
						"formation": [101005,101006,101007,101031,101022,101009,101011,101029]
					},	
					"2": {	
						"playerName": "General Gohan",
						"formation": [101008,101009,101010,101031,101011,101012,101025,101033]
					}	
				}		
			},			
			"115": {			
				"playerLevel": 115,		
				"npcLevel": 230,		
				"fakeDataFormation": {		
					"1": {	
						"playerName": "Legion Krillin",
						"formation": [101001,101002,101003,101011,101015,101007,101017,101027]
					},	
					"2": {	
						"playerName": "Amy No.17",
						"formation": [101005,101004,101009,101013,101019,101022,101025,101038]
					}	
				}		
			},			
			"116": {			
				"playerLevel": 116,		
				"npcLevel": 232,		
				"fakeDataFormation": {		
					"1": {	
						"playerName": "Hermit Wolf",
						"formation": [101011,101012,101013,101014,101015,101016,101017,101018]
					},	
					"2": {	
						"playerName": "Shen JR.",
						"formation": [101001,101002,101003,101004,101005,101006,101007,101008]
					}	
				}		
			},			
			"117": {			
				"playerLevel": 117,		
				"npcLevel": 234,		
				"fakeDataFormation": {		
					"1": {	
						"playerName": "Prince Rage",
						"formation": [101001,101002,101011,101013,101021,101015,101022,101041]
					},	
					"2": {	
						"playerName": "Shen King",
						"formation": [101003,101004,101005,101006,101007,101008,101009,101010]
					}	
				}		
			},			
			"118": {			
				"playerLevel": 118,		
				"npcLevel": 236,		
				"fakeDataFormation": {		
					"1": {	
						"playerName": "North Kai No.15",
						"formation": [101021,101022,101023,101024,101025,101026,101027,101028]
					},	
					"2": {	
						"playerName": "Jeice No.14",
						"formation": [101031,101032,101033,101034,101035,101036,101037,101038]
					}	
				}		
			},			
			"119": {			
				"playerLevel": 119,		
				"npcLevel": 238,		
				"fakeDataFormation": {		
					"1": {	
						"playerName": "Korin No.12",
						"formation": [101001,101011,101021,101031,101041,101002,101012,101022]
					},	
					"2": {	
						"playerName": "Baby Legion",
						"formation": [101001,101005,101010,101015,101020,101025,101030,101035]
					}	
				}		
			},			
			"120": {			
				"playerLevel": 120,		
				"npcLevel": 240,		
				"fakeDataFormation": {		
					"1": {	
						"playerName": "Dr. Wave",
						"formation": [101001,101002,101006,101008,101009,101011,101013,101015]
					},	
					"2": {	
						"playerName": "Captain No.9",
						"formation": [101003,101004,101012,101021,101019,101041,101042,101018]
					}	
				}		
			},			
			"121": {			
				"playerLevel": 121,		
				"npcLevel": 242,		
				"fakeDataFormation": {		
					"1": {	
						"playerName": "Krillin King",
						"formation": [101005,101006,101007,101031,101022,101009,101011,101029]
					},	
					"2": {	
						"playerName": "General Gohan",
						"formation": [101008,101009,101010,101031,101011,101012,101025,101033]
					}	
				}		
			},			
			"122": {			
				"playerLevel": 122,		
				"npcLevel": 244,		
				"fakeDataFormation": {		
					"1": {	
						"playerName": "Legion Krillin",
						"formation": [101001,101002,101003,101011,101015,101007,101017,101027]
					},	
					"2": {	
						"playerName": "Amy No.17",
						"formation": [101005,101004,101009,101013,101019,101022,101025,101038]
					}	
				}		
			},			
			"123": {			
				"playerLevel": 123,		
				"npcLevel": 246,		
				"fakeDataFormation": {		
					"1": {	
						"playerName": "Hermit Wolf",
						"formation": [101011,101012,101013,101014,101015,101016,101017,101018]
					},	
					"2": {	
						"playerName": "Shen JR.",
						"formation": [101001,101002,101003,101004,101005,101006,101007,101008]
					}	
				}		
			},			
			"124": {			
				"playerLevel": 124,		
				"npcLevel": 248,		
				"fakeDataFormation": {		
					"1": {	
						"playerName": "Prince Rage",
						"formation": [101001,101002,101011,101013,101021,101015,101022,101041]
					},	
					"2": {	
						"playerName": "Shen King",
						"formation": [101003,101004,101005,101006,101007,101008,101009,101010]
					}	
				}		
			},			
			"125": {			
				"playerLevel": 125,		
				"npcLevel": 250,		
				"fakeDataFormation": {		
					"1": {	
						"playerName": "North Kai No.15",
						"formation": [101021,101022,101023,101024,101025,101026,101027,101028]
					},	
					"2": {	
						"playerName": "Jeice No.14",
						"formation": [101031,101032,101033,101034,101035,101036,101037,101038]
					}	
				}		
			},			
			"126": {			
				"playerLevel": 126,		
				"npcLevel": 252,		
				"fakeDataFormation": {		
					"1": {	
						"playerName": "Korin No.12",
						"formation": [101001,101011,101021,101031,101041,101002,101012,101022]
					},	
					"2": {	
						"playerName": "Baby Legion",
						"formation": [101001,101005,101010,101015,101020,101025,101030,101035]
					}	
				}		
			},			
			"127": {			
				"playerLevel": 127,		
				"npcLevel": 254,		
				"fakeDataFormation": {		
					"1": {	
						"playerName": "Dr. Wave",
						"formation": [101001,101002,101006,101008,101009,101011,101013,101015]
					},	
					"2": {	
						"playerName": "Captain No.9",
						"formation": [101003,101004,101012,101021,101019,101041,101042,101018]
					}	
				}		
			},			
			"128": {			
				"playerLevel": 128,		
				"npcLevel": 256,		
				"fakeDataFormation": {		
					"1": {	
						"playerName": "Krillin King",
						"formation": [101005,101006,101007,101031,101022,101009,101011,101029]
					},	
					"2": {	
						"playerName": "General Gohan",
						"formation": [101008,101009,101010,101031,101011,101012,101025,101033]
					}	
				}		
			},			
			"129": {			
				"playerLevel": 129,		
				"npcLevel": 258,		
				"fakeDataFormation": {		
					"1": {	
						"playerName": "Legion Krillin",
						"formation": [101001,101002,101003,101011,101015,101007,101017,101027]
					},	
					"2": {	
						"playerName": "Amy No.17",
						"formation": [101005,101004,101009,101013,101019,101022,101025,101038]
					}	
				}		
			},			
			"130": {			
				"playerLevel": 130,		
				"npcLevel": 260,		
				"fakeDataFormation": {		
					"1": {	
						"playerName": "Hermit Wolf",
						"formation": [101011,101012,101013,101014,101015,101016,101017,101018]
					},	
					"2": {	
						"playerName": "Shen JR.",
						"formation": [101001,101002,101003,101004,101005,101006,101007,101008]
					}	
				}		
			},			
			"131": {			
				"playerLevel": 131,		
				"npcLevel": 262,		
				"fakeDataFormation": {		
					"1": {	
						"playerName": "Prince Rage",
						"formation": [101001,101002,101011,101013,101021,101015,101022,101041]
					},	
					"2": {	
						"playerName": "Shen King",
						"formation": [101003,101004,101005,101006,101007,101008,101009,101010]
					}	
				}		
			},			
			"132": {			
				"playerLevel": 132,		
				"npcLevel": 264,		
				"fakeDataFormation": {		
					"1": {	
						"playerName": "North Kai No.15",
						"formation": [101021,101022,101023,101024,101025,101026,101027,101028]
					},	
					"2": {	
						"playerName": "Jeice No.14",
						"formation": [101031,101032,101033,101034,101035,101036,101037,101038]
					}	
				}		
			},			
			"133": {			
				"playerLevel": 133,		
				"npcLevel": 266,		
				"fakeDataFormation": {		
					"1": {	
						"playerName": "Korin No.12",
						"formation": [101001,101011,101021,101031,101041,101002,101012,101022]
					},	
					"2": {	
						"playerName": "Baby Legion",
						"formation": [101001,101005,101010,101015,101020,101025,101030,101035]
					}	
				}		
			},			
			"134": {			
				"playerLevel": 134,		
				"npcLevel": 268,		
				"fakeDataFormation": {		
					"1": {	
						"playerName": "Dr. Wave",
						"formation": [101001,101002,101006,101008,101009,101011,101013,101015]
					},	
					"2": {	
						"playerName": "Captain No.9",
						"formation": [101003,101004,101012,101021,101019,101041,101042,101018]
					}	
				}		
			},			
			"135": {			
				"playerLevel": 135,		
				"npcLevel": 270,		
				"fakeDataFormation": {		
					"1": {	
						"playerName": "Krillin King",
						"formation": [101005,101006,101007,101031,101022,101009,101011,101029]
					},	
					"2": {	
						"playerName": "General Gohan",
						"formation": [101008,101009,101010,101031,101011,101012,101025,101033]
					}	
				}		
			},			
			"136": {			
				"playerLevel": 136,		
				"npcLevel": 272,		
				"fakeDataFormation": {		
					"1": {	
						"playerName": "Legion Krillin",
						"formation": [101001,101002,101003,101011,101015,101007,101017,101027]
					},	
					"2": {	
						"playerName": "Amy No.17",
						"formation": [101005,101004,101009,101013,101019,101022,101025,101038]
					}	
				}		
			},			
			"137": {			
				"playerLevel": 137,		
				"npcLevel": 274,		
				"fakeDataFormation": {		
					"1": {	
						"playerName": "Hermit Wolf",
						"formation": [101011,101012,101013,101014,101015,101016,101017,101018]
					},	
					"2": {	
						"playerName": "Shen JR.",
						"formation": [101001,101002,101003,101004,101005,101006,101007,101008]
					}	
				}		
			},			
			"138": {			
				"playerLevel": 138,		
				"npcLevel": 276,		
				"fakeDataFormation": {		
					"1": {	
						"playerName": "Prince Rage",
						"formation": [101001,101002,101011,101013,101021,101015,101022,101041]
					},	
					"2": {	
						"playerName": "Shen King",
						"formation": [101003,101004,101005,101006,101007,101008,101009,101010]
					}	
				}		
			},			
			"139": {			
				"playerLevel": 139,		
				"npcLevel": 278,		
				"fakeDataFormation": {		
					"1": {	
						"playerName": "North Kai No.15",
						"formation": [101021,101022,101023,101024,101025,101026,101027,101028]
					},	
					"2": {	
						"playerName": "Jeice No.14",
						"formation": [101031,101032,101033,101034,101035,101036,101037,101038]
					}	
				}		
			},			
			"140": {			
				"playerLevel": 140,		
				"npcLevel": 280,		
				"fakeDataFormation": {		
					"1": {	
						"playerName": "Korin No.12",
						"formation": [101001,101011,101021,101031,101041,101002,101012,101022]
					},	
					"2": {	
						"playerName": "Baby Legion",
						"formation": [101001,101005,101010,101015,101020,101025,101030,101035]
					}	
				}		
			},			
			"141": {			
				"playerLevel": 141,		
				"npcLevel": 282,		
				"fakeDataFormation": {		
					"1": {	
						"playerName": "Dr. Wave",
						"formation": [101001,101002,101006,101008,101009,101011,101013,101015]
					},	
					"2": {	
						"playerName": "Captain No.9",
						"formation": [101003,101004,101012,101021,101019,101041,101042,101018]
					}	
				}		
			},			
			"142": {			
				"playerLevel": 142,		
				"npcLevel": 284,		
				"fakeDataFormation": {		
					"1": {	
						"playerName": "Krillin King",
						"formation": [101005,101006,101007,101031,101022,101009,101011,101029]
					},	
					"2": {	
						"playerName": "General Gohan",
						"formation": [101008,101009,101010,101031,101011,101012,101025,101033]
					}	
				}		
			},			
			"143": {			
				"playerLevel": 143,		
				"npcLevel": 286,		
				"fakeDataFormation": {		
					"1": {	
						"playerName": "Legion Krillin",
						"formation": [101001,101002,101003,101011,101015,101007,101017,101027]
					},	
					"2": {	
						"playerName": "Amy No.17",
						"formation": [101005,101004,101009,101013,101019,101022,101025,101038]
					}	
				}		
			},			
			"144": {			
				"playerLevel": 144,		
				"npcLevel": 288,		
				"fakeDataFormation": {		
					"1": {	
						"playerName": "Hermit Wolf",
						"formation": [101011,101012,101013,101014,101015,101016,101017,101018]
					},	
					"2": {	
						"playerName": "Shen JR.",
						"formation": [101001,101002,101003,101004,101005,101006,101007,101008]
					}	
				}		
			},			
			"145": {			
				"playerLevel": 145,		
				"npcLevel": 290,		
				"fakeDataFormation": {		
					"1": {	
						"playerName": "Prince Rage",
						"formation": [101001,101002,101011,101013,101021,101015,101022,101041]
					},	
					"2": {	
						"playerName": "Shen King",
						"formation": [101003,101004,101005,101006,101007,101008,101009,101010]
					}	
				}		
			},			
			"146": {			
				"playerLevel": 146,		
				"npcLevel": 292,		
				"fakeDataFormation": {		
					"1": {	
						"playerName": "North Kai No.15",
						"formation": [101021,101022,101023,101024,101025,101026,101027,101028]
					},	
					"2": {	
						"playerName": "Jeice No.14",
						"formation": [101031,101032,101033,101034,101035,101036,101037,101038]
					}	
				}		
			},			
			"147": {			
				"playerLevel": 147,		
				"npcLevel": 294,		
				"fakeDataFormation": {		
					"1": {	
						"playerName": "Korin No.12",
						"formation": [101001,101011,101021,101031,101041,101002,101012,101022]
					},	
					"2": {	
						"playerName": "Baby Legion",
						"formation": [101001,101005,101010,101015,101020,101025,101030,101035]
					}	
				}		
			},			
			"148": {			
				"playerLevel": 148,		
				"npcLevel": 296,		
				"fakeDataFormation": {		
					"1": {	
						"playerName": "Dr. Wave",
						"formation": [101001,101002,101006,101008,101009,101011,101013,101015]
					},	
					"2": {	
						"playerName": "Captain No.9",
						"formation": [101003,101004,101012,101021,101019,101041,101042,101018]
					}	
				}		
			},			
			"149": {			
				"playerLevel": 149,		
				"npcLevel": 298,		
				"fakeDataFormation": {		
					"1": {	
						"playerName": "Krillin King",
						"formation": [101005,101006,101007,101031,101022,101009,101011,101029]
					},	
					"2": {	
						"playerName": "General Gohan",
						"formation": [101008,101009,101010,101031,101011,101012,101025,101033]
					}	
				}		
			},			
			"150": {			
				"playerLevel": 150,		
				"npcLevel": 300,		
				"fakeDataFormation": {		
					"1": {	
						"playerName": "Legion Krillin",
						"formation": [101001,101002,101003,101011,101015,101007,101017,101027]
					},	
					"2": {	
						"playerName": "Amy No.17",
						"formation": [101005,101004,101009,101013,101019,101022,101025,101038]
					}	
				}		
			},			
			"151": {			
				"playerLevel": 151,		
				"npcLevel": 302,		
				"fakeDataFormation": {		
					"1": {	
						"playerName": "Hermit Wolf",
						"formation": [101011,101012,101013,101014,101015,101016,101017,101018]
					},	
					"2": {	
						"playerName": "Shen JR.",
						"formation": [101001,101002,101003,101004,101005,101006,101007,101008]
					}	
				}		
			},			
			"152": {			
				"playerLevel": 152,		
				"npcLevel": 304,		
				"fakeDataFormation": {		
					"1": {	
						"playerName": "Prince Rage",
						"formation": [101001,101002,101011,101013,101021,101015,101022,101041]
					},	
					"2": {	
						"playerName": "Shen King",
						"formation": [101003,101004,101005,101006,101007,101008,101009,101010]
					}	
				}		
			}			
		}
	}
}